{
  "hash": "e9a07a43709981634f8742bd63645792",
  "result": {
    "markdown": "---\nformat:\n  html:\n    code-copy: true\ntitle: \"Response to “Nature fix: Addiction to outdoor activities\"\ndescription: \"A response to a commentary on our study of withdrwawal experiences in extreme sports exponents\"\nauthor:\n- name: Rob Heirene\n- name: David Shearer\n- name: Gareth Roderique-Davies\n- name: Stephen Mellalieu\ncategories: [Extreme sport]\ndate: 2016-12-01\nimage: featured.jpg\ndraft: false\n---\n\n### Abstract\n\nBuckley's commentary on our study of rock climber's withdrawal experiences raises a number of important questions surrounding the concept of extreme or adventure sports addiction. Drawing on the few available investigations of this topic, we respond to Buckley's questions here, though emphasize the need for further studies of extreme sports addiction in order to provide more empirically informed answers.\n\n------------------------------------------------------------------------\n\n**Full citation:**\n\n\n```{text, white-space: pre-wrap}\nHeirene, R. M., Shearer, D., Mellalieu, S. D. & Roderique-Davies, G. (2016). Response to “Nature fix: Addiction to outdoor activities”R. C. Buckley’s commentary on Heirene, R. M., Shearer, D., Roderique-Davies, G., & Mellalieu, S. D. (2016). Addiction in extreme sports: An exploration of withdrawal states in rock climbers. Journal of Behavioral Addictions, 5, 332-341. Journal of Behavioral Addictions, 5 (4), 559–561. https://doi.org/10.1556/2006.5.2016.087\n```\n\n\n**Full text:**\n\n-   Access pdf [here](HeireneExtremeSportsAddicResponse.pdf)\n\n",
    "supporting": [
      "index_files"
    ],
    "filters": [],
    "includes": {}
  }
}